supersuit/__init__.py
supersuit/aec_vector/__init__.py
supersuit/aec_vector/async_vector_env.py
supersuit/aec_vector/base_aec_vec_env.py
supersuit/aec_vector/create.py
supersuit/aec_vector/vector_env.py
supersuit/generic_wrappers/__init__.py
supersuit/generic_wrappers/basic_wrappers.py
supersuit/generic_wrappers/delay_observations.py
supersuit/generic_wrappers/frame_skip.py
supersuit/generic_wrappers/frame_stack.py
supersuit/generic_wrappers/max_observation.py
supersuit/generic_wrappers/nan_wrappers.py
supersuit/generic_wrappers/sticky_actions.py
supersuit/generic_wrappers/utils/__init__.py
supersuit/generic_wrappers/utils/base_modifier.py
supersuit/generic_wrappers/utils/shared_wrapper_util.py
supersuit/lambda_wrappers/__init__.py
supersuit/lambda_wrappers/action_lambda.py
supersuit/lambda_wrappers/observation_lambda.py
supersuit/lambda_wrappers/reward_lambda.py
supersuit/multiagent_wrappers/__init__.py
supersuit/multiagent_wrappers/agent_indication.py
supersuit/multiagent_wrappers/black_death.py
supersuit/multiagent_wrappers/padding_wrappers.py
supersuit/utils/__init__.py
supersuit/utils/accumulator.py
supersuit/utils/agent_indicator.py
supersuit/utils/base_aec_wrapper.py
supersuit/utils/convert_box.py
supersuit/utils/frame_skip.py
supersuit/utils/frame_stack.py
supersuit/utils/make_defaultdict.py
supersuit/utils/obs_delay.py
supersuit/utils/wrapper_chooser.py
supersuit/utils/action_transforms/__init__.py
supersuit/utils/action_transforms/homogenize_ops.py
supersuit/utils/basic_transforms/__init__.py
supersuit/utils/basic_transforms/color_reduction.py
supersuit/utils/basic_transforms/dtype.py
supersuit/utils/basic_transforms/flatten.py
supersuit/utils/basic_transforms/normalize_obs.py
supersuit/utils/basic_transforms/reshape.py
supersuit/utils/basic_transforms/resize.py
supersuit/vector/__init__.py
supersuit/vector/concat_vec_env.py
supersuit/vector/constructors.py
supersuit/vector/markov_vector_wrapper.py
supersuit/vector/multiproc_vec.py
SuperSuit-3.9.3.dist-info/LICENSE
SuperSuit-3.9.3.dist-info/METADATA
SuperSuit-3.9.3.dist-info/WHEEL
SuperSuit-3.9.3.dist-info/top_level.txt
SuperSuit-3.9.3.dist-info/RECORD
