Metadata-Version: 2.1
Name: SuperSuit
Version: 3.9.3
Summary: Wrappers for Gymnasium and PettingZoo
Author-email: Farama Foundation <contact@farama.org>
License: MIT License
Project-URL: Homepage, https://farama.org
Project-URL: Repository, https://github.com/Farama-Foundation/SuperSuit
Project-URL: Bug Report, https://github.com/Farama-Foundation/SuperSuit/issues
Keywords: Reinforcement Learning,game,RL,AI,gymnasium
Classifier: Programming Language :: Python :: 3.12
Classifier: Programming Language :: Python :: 3.11
Classifier: Programming Language :: Python :: 3.10
Classifier: Programming Language :: Python :: 3.9
Classifier: Programming Language :: Python :: 3.8
Classifier: License :: OSI Approved :: MIT License
Classifier: Operating System :: OS Independent
Requires-Python: >=3.8
License-File: LICENSE
Requires-Dist: numpy>=1.19.0
Requires-Dist: gymnasium>=0.28.1
Requires-Dist: tinyscaler>=1.2.6
Provides-Extra: testing
Requires-Dist: pettingzoo[all,atari]>=1.23.1; extra == "testing"
Requires-Dist: AutoROM; extra == "testing"
Requires-Dist: pytest; extra == "testing"
Requires-Dist: pytest-xdist; extra == "testing"
Requires-Dist: stable-baselines3>=2.0.0; extra == "testing"
Requires-Dist: moviepy>=1.0.0; extra == "testing"
